blockflow/__init__.py
blockflow/compile/__init__.py
blockflow/compile/circuit.py
blockflow/compile/export_qasm.py
blockflow/compile/optimizers.py
blockflow/compile/synthesis.py
blockflow/primitives/__init__.py
blockflow/primitives/block_encoding.py
blockflow/primitives/capabilities.py
blockflow/primitives/linear_operator.py
blockflow/primitives/recipe.py
blockflow/primitives/resources.py
blockflow/primitives/success.py
blockflow/primitives/vector_encoding.py
blockflow/programs/__init__.py
blockflow/programs/program.py
blockflow/semantic/__init__.py
blockflow/semantic/executor.py
blockflow/semantic/state.py
blockflow/semantic/tracking.py
qublock-0.1.0.dist-info/licenses/LICENSE
qublock-0.1.0.dist-info/METADATA
qublock-0.1.0.dist-info/WHEEL
qublock-0.1.0.dist-info/top_level.txt
qublock-0.1.0.dist-info/RECORD
