Metadata-Version: 2.4
Name: qublock
Version: 0.1.0
Summary: Block-encoding primitives and semantic execution for classical simulation.
Author-email: Ethan Feldman <ethanfeldman23@gmail.com>
License: MIT License
Project-URL: Homepage, https://github.com/EthanFeld/QuBlock
Project-URL: Issues, https://github.com/EthanFeld/QuBlock/issues
Project-URL: Repository, https://github.com/EthanFeld/QuBlock
Classifier: Development Status :: 3 - Alpha
Classifier: Intended Audience :: Science/Research
Classifier: License :: OSI Approved :: MIT License
Classifier: Programming Language :: Python :: 3
Classifier: Programming Language :: Python :: 3 :: Only
Classifier: Programming Language :: Python :: 3.9
Classifier: Programming Language :: Python :: 3.10
Classifier: Programming Language :: Python :: 3.11
Classifier: Programming Language :: Python :: 3.12
Classifier: Topic :: Scientific/Engineering :: Physics
Requires-Python: >=3.9
License-File: LICENSE
Requires-Dist: numpy>=1.22
Provides-Extra: dev
Requires-Dist: pytest>=7.0; extra == "dev"
Requires-Dist: pytest-cov>=4.0; extra == "dev"
Requires-Dist: ruff>=0.6.0; extra == "dev"
Dynamic: license-file
